ibis_vega_transform/__init__.py
ibis_vega_transform/_version.py
ibis_vega_transform/altair_data_transformer.py
ibis_vega_transform/altair_monkeypatch.py
ibis_vega_transform/altair_renderer.py
ibis_vega_transform/compiler.py
ibis_vega_transform/core.py
ibis_vega_transform/globals.py
ibis_vega_transform/query.py
ibis_vega_transform/tracer.py
ibis_vega_transform/util.py
ibis_vega_transform/vegaexpr.py
ibis_vega_transform/labextension/package.json
ibis_vega_transform/labextension/static/156.2c8fdf0ea030f880bbef.js
ibis_vega_transform/labextension/static/160.7808d10618258fab30b6.js
ibis_vega_transform/labextension/static/160.7808d10618258fab30b6.js.LICENSE.txt
ibis_vega_transform/labextension/static/161.1a6b061129d2a15372a0.js
ibis_vega_transform/labextension/static/176.752be57578d2d1f570d9.js
ibis_vega_transform/labextension/static/36.73511dd75ce30da91ed0.js
ibis_vega_transform/labextension/static/534.59a89e692729233b6e57.js
ibis_vega_transform/labextension/static/581.a52396581f9adaa4542a.js
ibis_vega_transform/labextension/static/707.69acfa97221a5719f6c4.js
ibis_vega_transform/labextension/static/823.fd94bbb96b842d6a82c1.js
ibis_vega_transform/labextension/static/942.788fcae1fd41e1d18c0f.js
ibis_vega_transform/labextension/static/990.979eec5b10c285d3079d.js
ibis_vega_transform/labextension/static/remoteEntry.12b92336585a8814945b.js
ibis_vega_transform/labextension/static/style.js
ibis_vega_transform/transforms/__init__.py
ibis_vega_transform/transforms/aggregate.py
ibis_vega_transform/transforms/bin.py
ibis_vega_transform/transforms/collect.py
ibis_vega_transform/transforms/filter.py
ibis_vega_transform/transforms/formula.py
ibis_vega_transform/transforms/timeunit.py
ibis_vega_transform-5.3.0.data/data/etc/jupyter/jupyter_server_config.d/ibis_vega_transform.json
ibis_vega_transform-5.3.0.data/data/share/jupyter/labextensions/ibis-vega-transform/install.json
ibis_vega_transform-5.3.0.data/data/share/jupyter/labextensions/ibis-vega-transform/package.json
ibis_vega_transform-5.3.0.dist-info/AUTHORS.md
ibis_vega_transform-5.3.0.dist-info/LICENSE.txt
ibis_vega_transform-5.3.0.dist-info/METADATA
ibis_vega_transform-5.3.0.dist-info/WHEEL
ibis_vega_transform-5.3.0.dist-info/top_level.txt
ibis_vega_transform-5.3.0.dist-info/RECORD
