Metadata-Version: 2.1
Name: ibis-vega-transform
Version: 5.3.0
Summary: Evaluate Vega transforms using Ibis expressions.
Home-page: https://github.com/Quansight/ibis-vega-transform
Author: OmniSci/Quansight
License: Apache-2.0
Keywords: Jupyter,JupyterLab,JupyterLab3
Platform: Linux
Platform: Mac OS X
Platform: Windows
Classifier: License :: OSI Approved :: BSD License
Classifier: Programming Language :: Python
Classifier: Programming Language :: Python :: 3
Classifier: Programming Language :: Python :: 3.7
Classifier: Framework :: Jupyter
Requires-Python: >=3.7,<3.9
Requires-Dist: jupyterlab (==3.*,>=3.0.0rc13)
Requires-Dist: setuptools (>=46.4.0)
Requires-Dist: altair (>=4.0.0)
Requires-Dist: altair-transform
Requires-Dist: ibis-framework (>=1.3.0)
Requires-Dist: jaeger-client
Requires-Dist: jupyter-jaeger (>=1.0.4)
Requires-Dist: jupyterlab-server
Requires-Dist: mypy-extensions
Requires-Dist: nbclassic (>=0.2)
Requires-Dist: opentracing
Requires-Dist: pymapd (>=0.24)
Requires-Dist: sqlalchemy (<1.4)
Requires-Dist: tornado
Requires-Dist: typing-extensions
Requires-Dist: vega-datasets
